table2string/__init__.py
table2string/aligns.py
table2string/table2string.py
table2string/themes.py
table2string/utils.py
table2string-2.0.1.dist-info/METADATA
table2string-2.0.1.dist-info/WHEEL
table2string-2.0.1.dist-info/licenses/LICENSE
table2string-2.0.1.dist-info/RECORD
