Metadata-Version: 2.3
Name: table2string
Version: 2.0.1
Summary: A library to convert tables to string with full support for line breaks and formatting
Project-URL: Homepage, https://github.com/EgorKhabarov/table2string
Project-URL: Documentation, https://github.com/EgorKhabarov/table2string
Project-URL: Repository, https://github.com/EgorKhabarov/table2string
Project-URL: Issues, https://github.com/EgorKhabarov/table2string/issues
Author-email: EgorKhabarov <not.a.fan.of.broccoli@gmail.com>
License: GPL2
License-File: LICENSE
Keywords: string,table,tools
Classifier: Development Status :: 5 - Production/Stable
Classifier: Environment :: Console
Classifier: License :: OSI Approved :: GNU General Public License v2 (GPLv2)
Classifier: Programming Language :: Python :: 3
Classifier: Programming Language :: Python :: 3.7
Classifier: Programming Language :: Python :: 3.8
Classifier: Programming Language :: Python :: 3.9
Classifier: Programming Language :: Python :: 3.10
Classifier: Programming Language :: Python :: 3.11
Classifier: Programming Language :: Python :: 3.12
Requires-Python: >=3.7
